{
  "type": "Periodic transaction report",
  "title": "",
  "filer": "Mark Warner (Virginia)",
  "filed-date": "2014-06-17",
  "filed-time": "13:16",
  "data": [
    {
      "heading": "Transactions",
      "amended": false,
      "rows": [
        {
          "owner": "Self",
          "asset-name": "DubMeNow, Inc",
          "ticker": "",
          "transaction-type": "Purchase",
          "transaction-date": "2014-05-30",
          "amount": "$100,001 - $250,000"
        }
      ]
    }
  ]
}