{
  "type": "annual report",
  "title": "Annual Report for Calendar 2013",
  "filer": "The Honorable Charles E Grassley (Grassley, Charles E.)",
  "filed-date": "05/15/2014",
  "filed-time": "6:08 AM",
  "calendar-year": "2013",
  "data-entry-complete": true,
  "data": [
    {
      "heading": "Part 1. Honoraria Payments or Payments to Charity in Lieu of Honoraria",
      "amended": false,
      "rows": []
    },
    {
      "heading": "Part 2. Earned and Non-Investment Income",
      "amended": false,
      "rows": [
        {
          "who-was-paid": "Spouse",
          "type": "Salary",
          "who-paid": "Chambers, Conlon & Hartwell\n\t\t\t\t\t\t\t\tWashington, DC",
          "amount-paid": "> $1,000"
        },
        {
          "who-was-paid": "Spouse",
          "type": "Retirement",
          "who-paid": "Raymond James Trust IRA\n\t\t\t\t\t\t\t\tSt Petersburg , FL",
          "amount-paid": "> $1,000"
        },
        {
          "who-was-paid": "Self",
          "type": "Retirement",
          "who-paid": "Raymond James Trust IRA\n\t\t\t\t\t\t\t\tSt Petersburg , FL",
          "amount-paid": "$25,570.99"
        }
      ]
    },
    {
      "heading": "Part 3. Assets",
      "amended": false,
      "rows": [
        {
          "asset": "Farmer's Cooperative Co.Description: Cooperative (New Hartford, Iowa)",
          "asset-type": "Farm",
          "owner": "Joint",
          "value": "$1,001 - $15,000",
          "income-type": "Dividends",
          "income": "$201 - $1,000"
        },
        {
          "asset": "Value First Co-operativeDescription: Farm Co-operative (Wellsburg, Iowa)",
          "asset-type": "Farm",
          "owner": "Self",
          "value": "$1,001 - $15,000",
          "income-type": "Dividends",
          "income": "$5,001 - $15,000"
        },
        {
          "asset": "Farm Land-all located in Butler County, Iowa, Beaver TownshipDescription: Sec. 16, Rng. 15-118 A (New Hartford, Iowa) Filer comment:  Combined Farm Income $276,125 less Combined Farm Expense $126,837=Net Income $149,738.00",
          "asset-type": "Farm",
          "owner": "Joint",
          "value": "$100,001 - $250,000",
          "income-type": "Other, (Grain Sales)",
          "income": "Other $149,738.00"
        },
        {
          "asset": "Farm Land-all located in Butler County, Iowa, Beaver TownshipDescription: Sec. 24, Rng. 15-72 A (New Hartford, Iowa) Filer comment:  Combined Farm Income less Combined Farm Expense=Net Income $149,738.00",
          "asset-type": "Farm",
          "owner": "Joint",
          "value": "$50,001 - $100,000",
          "income-type": "Other, (Grain Sales)",
          "income": "Other $149,738.00"
        },
        {
          "asset": "Farm Land-All located in Butler County, Iowa, Beaver TownshipDescription: Sec. 34, Rng. 15 - 40 A (New Hartford, Iowa) Filer comment:  Combined Farm Income $276,125 less Combined Farm Expense $126,387=Net Income $149,738.00",
          "asset-type": "Farm",
          "owner": "Joint",
          "value": "$100,001 - $250,000",
          "income-type": "Other, (Grain Sales)",
          "income": "Other $149,738.00"
        },
        {
          "asset": "Farm Land-All Located in Butler County, Iowa, Beaver TownshipDescription: Sec. 15, Rng. 15-43 A (New Hartford, Iowa) Filer comment:  Combined Farm Income $276,125 less Combined Farm Expenses $126,387=Net Income $149,738.00",
          "asset-type": "Farm",
          "owner": "Joint",
          "value": "$50,001 - $100,000",
          "income-type": "Other, (Grain Sales)",
          "income": "Other $149,738.00"
        },
        {
          "asset": "Farm Land-All located in Butler County, Iowa, Beaver TownshipDescription: Sec. 15, Rng. 15-87 A (New Hartford, Iowa) Filer comment:  Combined Farm Income less Combined Farm Expense=Net Income $149,738.00",
          "asset-type": "Farm",
          "owner": "Joint",
          "value": "$100,001 - $250,000",
          "income-type": "Other, (Grain Sales)",
          "income": "Other $149,738.00"
        },
        {
          "asset": "Farm Land-All located in Butler County, Iowa, Beaver TownshipDescription: Sec. 34, Rng.15 -114 A (New Hartford, Iowa) Filer comment:  Combined Farm Income less Combined Farm Expense=Net Income $149,738.00\nInadvertently reported as tract 15-104 in previous reports.",
          "asset-type": "Farm",
          "owner": "Joint",
          "value": "$100,001 - $250,000",
          "income-type": "Other, (Grain Sales)",
          "income": "Other $149,738.00"
        },
        {
          "asset": "Farm Land-All located in Butler County, Iowa, Beaver TownshipDescription: Sec. 34 & 35, Rng. 18-120 A (New Hartford, Iowa) Filer comment:  Combined Farm Income less Combined Farm Expense=Net Income $149,738.00",
          "asset-type": "Farm",
          "owner": "Joint",
          "value": "$100,001 - $250,000",
          "income-type": "Other, (Grain Sales)",
          "income": "Other $149,738.00"
        },
        {
          "asset": "Farm Land-All Located in Butler County, Iowa, Beaver TownshipDescription: Sec. 34, Rng. 15 - 118 A (New Hartford, Iowa) Filer comment:  Combined Farm Income-$276,125 less Combined Farm Expense -$126,387 = Net Income $149,738.00",
          "asset-type": "Farm",
          "owner": "Joint",
          "value": "$100,001 - $250,000",
          "income-type": "Other, (Grain Sales)",
          "income": "Other $149,738.00"
        },
        {
          "asset": "Farm Land-All located in Butler County, Iowa, Beaver TownshipDescription: Sec. 16, Rng. 15 - 40 A (New Hartford, Iowa) Filer comment:  Combined Farm Income less Combined Farm Expense=Net Income $149,738.00",
          "asset-type": "Farm",
          "owner": "Joint",
          "value": "$15,001 - $50,000",
          "income-type": "Other, (Grain Sales)",
          "income": "Other $149,738.00"
        },
        {
          "asset": "Moderate Growth Age-based Track 19 & older Money MarketInstitution: Iowa-managed by Vangard",
          "asset-type": "Education Savings Plans529 College Savings Plan",
          "owner": "Self",
          "value": "$50,001 - $100,000",
          "income-type": "Excepted Investment Fund",
          "income": "None (or less than $201)"
        },
        {
          "asset": "Moderate Growth Age-based Track-16-18 Income PortfolioInstitution: Iowa-managed by Vangard",
          "asset-type": "Education Savings Plans529 College Savings Plan",
          "owner": "Self",
          "value": "$15,001 - $50,000",
          "income-type": "Excepted Investment Fund",
          "income": "None (or less than $201)"
        },
        {
          "asset": "Moderate-growth Age-based Track 19 & OlderInstitution: Iowa-managed by Vangard",
          "asset-type": "Education Savings Plans529 College Savings Plan",
          "owner": "Spouse",
          "value": "$50,001 - $100,000",
          "income-type": "Excepted Investment Fund",
          "income": "None (or less than $201)"
        },
        {
          "asset": "Moderate Growth Age-based Track 16-18 Income PortfolioInstitution: Iowa-managed by Vangard",
          "asset-type": "Education Savings Plans529 College Savings Plan",
          "owner": "Spouse",
          "value": "$15,001 - $50,000",
          "income-type": "Excepted Investment Fund",
          "income": "None (or less than $201)"
        },
        {
          "asset": "Property Sale-2 acre FarmsteadDebtor: Robin & Diane Grassley",
          "asset-type": "Accounts ReceivableFrom an Individual",
          "owner": "Joint",
          "value": "$1,001 - $15,000",
          "income-type": "Interest",
          "income": "$201 - $1,000"
        },
        {
          "asset": "New York Life Insurance Provider: New York Life Insurance",
          "asset-type": "Life InsuranceWhole",
          "owner": "Self",
          "value": "$1,001 - $15,000",
          "income-type": "Dividends",
          "income": "None (or less than $201)"
        },
        {
          "asset": "New York Life InsuranceProvider: New York Life Insurance",
          "asset-type": "Life InsuranceWhole",
          "owner": "Self",
          "value": "$1,001 - $15,000",
          "income-type": "Dividends",
          "income": "None (or less than $201)"
        },
        {
          "asset": "Ohio National Life InsuranceProvider: Ohio National Life Insurance",
          "asset-type": "Life InsuranceWhole",
          "owner": "Self",
          "value": "$1,001 - $15,000",
          "income-type": "Dividends",
          "income": "None (or less than $201)"
        },
        {
          "asset": "Ohio National Life InsurnceProvider: Ohio National Life Insurance",
          "asset-type": "Life InsuranceWhole",
          "owner": "Self",
          "value": "$1,001 - $15,000",
          "income-type": "Dividends",
          "income": "None (or less than $201)"
        },
        {
          "asset": "AMRMX - American Funds American Mutual A (NASDAQ)",
          "asset-type": "Mutual FundsMutual Fund",
          "owner": "Spouse",
          "value": "$15,001 - $50,000",
          "income-type": "Excepted Investment Fund",
          "income": "$201 - $1,000"
        },
        {
          "asset": "ING 401k Plan",
          "asset-type": "Retirement PlansDefined Contribution Pension Plan",
          "owner": "Spouse",
          "value": "",
          "income-type": "",
          "income": ""
        },
        {
          "asset": "Oppenheimer Int. Bond Fnd A",
          "asset-type": "Mutual FundsMutual Fund",
          "owner": "Spouse",
          "value": "$15,001 - $50,000",
          "income-type": "Excepted Investment Fund",
          "income": "None (or less than $201)"
        },
        {
          "asset": "ING TRowe Price Cap Apprec Pt Srv",
          "asset-type": "Mutual FundsMutual Fund",
          "owner": "Spouse",
          "value": "$100,001 - $250,000",
          "income-type": "Excepted Investment Fund",
          "income": "None (or less than $201)"
        },
        {
          "asset": "ING Index Plus Large Cap Port 1",
          "asset-type": "Mutual FundsMutual Fund",
          "owner": "Spouse",
          "value": "$15,001 - $50,000",
          "income-type": "Excepted Investment Fund",
          "income": "None (or less than $201)"
        },
        {
          "asset": "ING Fidelity VIP Contrafund Port Srv",
          "asset-type": "Mutual FundsMutual Fund",
          "owner": "Spouse",
          "value": "$15,001 - $50,000",
          "income-type": "Excepted Investment Fund",
          "income": "None (or less than $201)"
        },
        {
          "asset": "AllianzGI NFJ Div. Value Fd Inst",
          "asset-type": "Mutual FundsMutual Fund",
          "owner": "Spouse",
          "value": "$50,001 - $100,000",
          "income-type": "Excepted Investment Fund",
          "income": "None (or less than $201)"
        },
        {
          "asset": "American Funds Growth Fnd R3",
          "asset-type": "Mutual FundsMutual Fund",
          "owner": "Spouse",
          "value": "$50,001 - $100,000",
          "income-type": "Excepted Investment Fund",
          "income": "None (or less than $201)"
        },
        {
          "asset": "ING Fidelity VIP Mid Cap Port Srv",
          "asset-type": "Mutual FundsMutual Fund",
          "owner": "Spouse",
          "value": "$15,001 - $50,000",
          "income-type": "Excepted Investment Fund",
          "income": "None (or less than $201)"
        },
        {
          "asset": "Oppenheimer Main St Sm Cap F/VA",
          "asset-type": "Mutual FundsMutual Fund",
          "owner": "Spouse",
          "value": "$15,001 - $50,000",
          "income-type": "Excepted Investment Fund",
          "income": "None (or less than $201)"
        },
        {
          "asset": "Columbia Mid Cap Value Fund A",
          "asset-type": "Mutual FundsMutual Fund",
          "owner": "Spouse",
          "value": "$15,001 - $50,000",
          "income-type": "Excepted Investment Fund",
          "income": "None (or less than $201)"
        },
        {
          "asset": "American Funds Euro Pacific R3",
          "asset-type": "Mutual FundsMutual Fund",
          "owner": "Spouse",
          "value": "$50,001 - $100,000",
          "income-type": "Excepted Investment Fund",
          "income": "None (or less than $201)"
        },
        {
          "asset": "Lazard Emerging Mkts Eqty Port Opn",
          "asset-type": "Mutual FundsMutual Fund",
          "owner": "Spouse",
          "value": "$15,001 - $50,000",
          "income-type": "Excepted Investment Fund",
          "income": "None (or less than $201)"
        },
        {
          "asset": "ING FIXED ACCOUNTProvider: ING",
          "asset-type": "AnnuityFixed",
          "owner": "Spouse",
          "value": "$50,001 - $100,000",
          "income-type": "None, Interest",
          "income": "None (or less than $201)"
        },
        {
          "asset": "Community Bank & Trust (formerly Communiy National Bank)(Waterloo, IA)Type: Checking",
          "asset-type": "Bank Deposit",
          "owner": "Joint",
          "value": "$1,001 - $15,000",
          "income-type": "Interest",
          "income": "None (or less than $201)"
        },
        {
          "asset": "Community Bank & Trust (formerly Communiy National Bank)(Waterloo, Iowa)Type: Savings",
          "asset-type": "Bank Deposit",
          "owner": "Joint",
          "value": "$1,001 - $15,000",
          "income-type": "Interest",
          "income": "None (or less than $201)"
        },
        {
          "asset": "BARBARA IRA  RJ",
          "asset-type": "Brokerage/Managed Account",
          "owner": "Spouse",
          "value": "",
          "income-type": "",
          "income": ""
        },
        {
          "asset": "CHTRX - Invesco Charter A (NASDAQ)",
          "asset-type": "Mutual FundsMutual Fund",
          "owner": "Spouse",
          "value": "$1,001 - $15,000",
          "income-type": "Excepted Investment Fund",
          "income": "None (or less than $201)"
        },
        {
          "asset": "IDITX - Transamerica Flexible Income A (NASDAQ)",
          "asset-type": "Mutual FundsMutual Fund",
          "owner": "Spouse",
          "value": "$1,001 - $15,000",
          "income-type": "Excepted Investment Fund",
          "income": "$201 - $1,000"
        },
        {
          "asset": "BDJ - Blackrock Enhanced Equity Divid (NYSE)",
          "asset-type": "Mutual FundsExchange Traded Fund/Note",
          "owner": "Spouse",
          "value": "$1,001 - $15,000",
          "income-type": "Excepted Investment Fund",
          "income": "$201 - $1,000"
        },
        {
          "asset": "RAYMOND JAMES BANK DEPOSIT PROGRAM(ST PETERSBURG, FL)Type: Brokerage Sweep Account",
          "asset-type": "Bank Deposit",
          "owner": "Spouse",
          "value": "None (or less than $1,001)",
          "income-type": "Interest",
          "income": "None (or less than $201)"
        },
        {
          "asset": "GRASSLEY FREEDOM",
          "asset-type": "Brokerage/Managed Account",
          "owner": "Joint",
          "value": "",
          "income-type": "",
          "income": ""
        },
        {
          "asset": "ALTVX - AllianceBern Muni Income Natl Adv (NASDAQ)",
          "asset-type": "Mutual FundsMutual Fund",
          "owner": "Joint",
          "value": "$1,001 - $15,000",
          "income-type": "Excepted Investment Fund",
          "income": "$201 - $1,000"
        },
        {
          "asset": "BIAGX - Brown Advisory Growth Equity Inv (NASDAQ)",
          "asset-type": "Mutual FundsMutual Fund",
          "owner": "Joint",
          "value": "$15,001 - $50,000",
          "income-type": "Excepted Investment Fund",
          "income": "None (or less than $201)"
        },
        {
          "asset": "ACINX - Columbia Acorn International Z (NASDAQ)",
          "asset-type": "Mutual FundsMutual Fund",
          "owner": "Joint",
          "value": "$1,001 - $15,000",
          "income-type": "Excepted Investment Fund",
          "income": "$201 - $1,000"
        },
        {
          "asset": "RRGAX - DWS RREEF Global Real Estate Secs A (NASDAQ)",
          "asset-type": "Mutual FundsMutual Fund",
          "owner": "Joint",
          "value": "$1,001 - $15,000",
          "income-type": "Excepted Investment Fund",
          "income": "$201 - $1,000"
        },
        {
          "asset": "EGEIX - Eagle Smaller Company I (NASDAQ)",
          "asset-type": "Mutual FundsMutual Fund",
          "owner": "Joint",
          "value": "$1,001 - $15,000",
          "income-type": "Excepted Investment Fund",
          "income": "None (or less than $201)"
        },
        {
          "asset": "AEGFX - American Funds EuroPacific Gr F1 (NASDAQ)",
          "asset-type": "Mutual FundsMutual Fund",
          "owner": "Joint",
          "value": "$1,001 - $15,000",
          "income-type": "Excepted Investment Fund",
          "income": "None (or less than $201)"
        },
        {
          "asset": "FLMVX - JPMorgan Mid Cap Value Instl (NASDAQ)",
          "asset-type": "Mutual FundsMutual Fund",
          "owner": "Joint",
          "value": "$1,001 - $15,000",
          "income-type": "Excepted Investment Fund",
          "income": "None (or less than $201)"
        },
        {
          "asset": "JVLAX - JHancock Disciplined Value A (NASDAQ)",
          "asset-type": "Mutual FundsMutual Fund",
          "owner": "Joint",
          "value": "$15,001 - $50,000",
          "income-type": "Excepted Investment Fund",
          "income": "None (or less than $201)"
        },
        {
          "asset": "JLPSX - JPMorgan US Large Cap Core Plus Select (NASDAQ)",
          "asset-type": "Mutual FundsMutual Fund",
          "owner": "Joint",
          "value": "$15,001 - $50,000",
          "income-type": "Excepted Investment Fund",
          "income": "None (or less than $201)"
        },
        {
          "asset": "MQGIX - MFS International Growth I (NASDAQ)",
          "asset-type": "Mutual FundsMutual Fund",
          "owner": "Joint",
          "value": "$1,001 - $15,000",
          "income-type": "Excepted Investment Fund",
          "income": "None (or less than $201)"
        },
        {
          "asset": "MFRFX - MFS Research A (NASDAQ)",
          "asset-type": "Mutual FundsMutual Fund",
          "owner": "Joint",
          "value": "$15,001 - $50,000",
          "income-type": "Excepted Investment Fund",
          "income": "None (or less than $201)"
        },
        {
          "asset": "MMHYX - MFS Municipal High-Income A (NASDAQ)",
          "asset-type": "Mutual FundsMutual Fund",
          "owner": "Joint",
          "value": "$1,001 - $15,000",
          "income-type": "Excepted Investment Fund",
          "income": "$201 - $1,000"
        },
        {
          "asset": "TSCPX - TimesSquare Small Cap Growth Prem (NASDAQ)",
          "asset-type": "Mutual FundsMutual Fund",
          "owner": "Joint",
          "value": "$15,001 - $50,000",
          "income-type": "Excepted Investment Fund",
          "income": "None (or less than $201)"
        },
        {
          "asset": "EXEYX - Manning & Napier Equity (NASDAQ)",
          "asset-type": "Mutual FundsMutual Fund",
          "owner": "Joint",
          "value": "$15,001 - $50,000",
          "income-type": "Excepted Investment Fund",
          "income": "None (or less than $201)"
        },
        {
          "asset": "NBGNX - Neuberger Berman Genesis Inv (NASDAQ)",
          "asset-type": "Mutual FundsMutual Fund",
          "owner": "Joint",
          "value": "$1,001 - $15,000",
          "income-type": "Excepted Investment Fund",
          "income": "None (or less than $201)"
        },
        {
          "asset": "PEGZX - Prudential Jennison Mid Cap Growth Z (NASDAQ)",
          "asset-type": "Mutual FundsMutual Fund",
          "owner": "Joint",
          "value": "$1,001 - $15,000",
          "income-type": "Excepted Investment Fund",
          "income": "None (or less than $201)"
        },
        {
          "asset": "PRINX - T. Rowe Price Summit Municipal Inc (NASDAQ)",
          "asset-type": "Mutual FundsMutual Fund",
          "owner": "Joint",
          "value": "$1,001 - $15,000",
          "income-type": "Excepted Investment Fund",
          "income": "$201 - $1,000"
        },
        {
          "asset": "HIEMX - Virtus Emerging Markets Opportunities I (NASDAQ)",
          "asset-type": "Mutual FundsMutual Fund",
          "owner": "Joint",
          "value": "$1,001 - $15,000",
          "income-type": "Excepted Investment Fund",
          "income": "None (or less than $201)"
        },
        {
          "asset": "WFVDX - Wells Fargo Advantage Intl Value Adm (NASDAQ)",
          "asset-type": "Mutual FundsMutual Fund",
          "owner": "Joint",
          "value": "$1,001 - $15,000",
          "income-type": "Excepted Investment Fund",
          "income": "$201 - $1,000"
        },
        {
          "asset": "AQMNX - AQR Managed Futures Strategy N (NASDAQ)",
          "asset-type": "Mutual FundsMutual Fund",
          "owner": "Joint",
          "value": "$15,001 - $50,000",
          "income-type": "Excepted Investment Fund",
          "income": "None (or less than $201)"
        },
        {
          "asset": "RAYMOND JAMES BANK DEPOSIT PROGRAM(ST PETERSBURG, FL)Type: Brokerage Sweep Account",
          "asset-type": "Bank Deposit",
          "owner": "Joint",
          "value": "$1,001 - $15,000",
          "income-type": "Interest",
          "income": "None (or less than $201)"
        },
        {
          "asset": "CHUCK SEP IRA",
          "asset-type": "Brokerage/Managed Account",
          "owner": "Self",
          "value": "",
          "income-type": "",
          "income": ""
        },
        {
          "asset": "ARIDX - ASTON/River Road Dividend All Cap Val I (NASDAQ)",
          "asset-type": "Mutual FundsMutual Fund",
          "owner": "Self",
          "value": "$15,001 - $50,000",
          "income-type": "Excepted Investment Fund",
          "income": "$1,001 - $2,500"
        },
        {
          "asset": "CAIFX - American Funds Capital Inc Bldr F2 (NASDAQ)",
          "asset-type": "Mutual FundsExchange Traded Fund/Note",
          "owner": "Self",
          "value": "$50,001 - $100,000",
          "income-type": "Excepted Investment Fund",
          "income": "$1,001 - $2,500"
        },
        {
          "asset": "RRGAX - DWS RREEF Global Real Estate Secs A (NASDAQ)",
          "asset-type": "Mutual FundsMutual Fund",
          "owner": "Self",
          "value": "$15,001 - $50,000",
          "income-type": "Excepted Investment Fund",
          "income": "$1,001 - $2,500"
        },
        {
          "asset": "SVAIX - Federated Strategic Value Dividend Instl (NASDAQ)",
          "asset-type": "Mutual FundsMutual Fund",
          "owner": "Self",
          "value": "$15,001 - $50,000",
          "income-type": "Excepted Investment Fund",
          "income": "$1,001 - $2,500"
        },
        {
          "asset": "FRIAX - Franklin Income Adv (NASDAQ)",
          "asset-type": "Mutual FundsMutual Fund",
          "owner": "Self",
          "value": "$15,001 - $50,000",
          "income-type": "Excepted Investment Fund",
          "income": "$2,501 - $5,000"
        },
        {
          "asset": "SOPAX - ClearBridge Equity Income A (NASDAQ)",
          "asset-type": "Mutual FundsMutual Fund",
          "owner": "Self",
          "value": "$15,001 - $50,000",
          "income-type": "Excepted Investment Fund",
          "income": "$201 - $1,000"
        },
        {
          "asset": "MMUFX - MFS Utilities A (NASDAQ)",
          "asset-type": "Mutual FundsMutual Fund",
          "owner": "Self",
          "value": "$15,001 - $50,000",
          "income-type": "Excepted Investment Fund",
          "income": "$201 - $1,000"
        },
        {
          "asset": "EPSPX - MainStay Epoch Global Equity Yield A (NASDAQ)",
          "asset-type": "Mutual FundsMutual Fund",
          "owner": "Self",
          "value": "$50,001 - $100,000",
          "income-type": "Excepted Investment Fund",
          "income": "$1,001 - $2,500"
        },
        {
          "asset": "PMDPX - Principal Small-MidCap Dividend Inc P (NASDAQ)",
          "asset-type": "Mutual FundsMutual Fund",
          "owner": "Self",
          "value": "$50,001 - $100,000",
          "income-type": "Excepted Investment Fund",
          "income": "$1,001 - $2,500"
        },
        {
          "asset": "PPSPX - Principal Preferred Securities P (NASDAQ)",
          "asset-type": "Mutual FundsMutual Fund",
          "owner": "Self",
          "value": "$15,001 - $50,000",
          "income-type": "Excepted Investment Fund",
          "income": "$2,501 - $5,000"
        },
        {
          "asset": "JDEZX - Prudential Jennison Equity Income Z (NASDAQ)",
          "asset-type": "Mutual FundsMutual Fund",
          "owner": "Self",
          "value": "$50,001 - $100,000",
          "income-type": "Excepted Investment Fund",
          "income": "$1,001 - $2,500"
        },
        {
          "asset": "GNEIX - Geneva Advisors Equity Income I (NASDAQ)",
          "asset-type": "Mutual FundsMutual Fund",
          "owner": "Self",
          "value": "$15,001 - $50,000",
          "income-type": "Excepted Investment Fund",
          "income": "$201 - $1,000"
        },
        {
          "asset": "RAYMOND JAMES BANK DEPOSIT PROGRAM(ST PETERSBURG, FL)Type: Brokerage Sweep Account",
          "asset-type": "Bank Deposit",
          "owner": "Self",
          "value": "$1,001 - $15,000",
          "income-type": "Interest",
          "income": "None (or less than $201)"
        },
        {
          "asset": "GRASSLEY CAPITAL ACCESS JOINT",
          "asset-type": "Brokerage/Managed Account",
          "owner": "Joint",
          "value": "",
          "income-type": "",
          "income": ""
        },
        {
          "asset": "NPM - Nuveen Premium Income Municipal (NYSE)",
          "asset-type": "Mutual FundsExchange Traded Fund/Note",
          "owner": "Joint",
          "value": "$1,001 - $15,000",
          "income-type": "Excepted Investment Fund",
          "income": "None (or less than $201)"
        },
        {
          "asset": "RAYMOND JAMES BANK DEPOSIT PROGRAM(ST PETERSBURG, FL)Type: Brokerage Sweep Account",
          "asset-type": "Bank Deposit",
          "owner": "Joint",
          "value": "$50,001 - $100,000",
          "income-type": "Interest",
          "income": "None (or less than $201)"
        },
        {
          "asset": "AXA EQUITABLE LIFE INS ACCUMULATORProvider: AXA",
          "asset-type": "AnnuityVariable Annuity",
          "owner": "Self",
          "value": "",
          "income-type": "",
          "income": ""
        },
        {
          "asset": "EQ/INT'L VALUE PLUS",
          "asset-type": "Mutual FundsMutual Fund",
          "owner": "Self",
          "value": "$15,001 - $50,000",
          "income-type": "Excepted Investment Fund",
          "income": "None (or less than $201)"
        },
        {
          "asset": "EQ/CORE BOND INDEX",
          "asset-type": "Mutual FundsMutual Fund",
          "owner": "Self",
          "value": "$1,001 - $15,000",
          "income-type": "Excepted Investment Fund",
          "income": "None (or less than $201)"
        },
        {
          "asset": "EQ/MID CAP VALUE PLUS",
          "asset-type": "Mutual FundsMutual Fund",
          "owner": "Self",
          "value": "$15,001 - $50,000",
          "income-type": "Excepted Investment Fund",
          "income": "None (or less than $201)"
        },
        {
          "asset": "EQ/EQUITY 500 INDEX",
          "asset-type": "Mutual FundsMutual Fund",
          "owner": "Self",
          "value": "$15,001 - $50,000",
          "income-type": "Excepted Investment Fund",
          "income": "None (or less than $201)"
        }
      ]
    },
    {
      "heading": "Part 4a. Periodic Transaction Report Summary",
      "amended": false,
      "rows": []
    },
    {
      "heading": "Part 4b. Transactions",
      "amended": false,
      "rows": [
        {
          "owner": "Self",
          "ticker": "ARIDX",
          "asset-name": "ASTON/River Road Dividend All Cap Val I (NASDAQ)",
          "transaction-type": "Purchase",
          "transaction-date": "04/04/2013",
          "amount": "$1,001 - $15,000",
          "comment": "--"
        },
        {
          "owner": "Self",
          "ticker": "MMUFX",
          "asset-name": "MFS Utilities A (NASDAQ)",
          "transaction-type": "Purchase",
          "transaction-date": "04/04/2013",
          "amount": "$1,001 - $15,000",
          "comment": "--"
        },
        {
          "owner": "Self",
          "ticker": "CAIFX",
          "asset-name": "American Funds Capital Inc Bldr F2 (NASDAQ)",
          "transaction-type": "Purchase",
          "transaction-date": "04/04/2013",
          "amount": "$1,001 - $15,000",
          "comment": "--"
        },
        {
          "owner": "Self",
          "ticker": "EPSPX",
          "asset-name": "MainStay Epoch Global Equity Yield A (NASDAQ)",
          "transaction-type": "Purchase",
          "transaction-date": "04/04/2013",
          "amount": "$1,001 - $15,000",
          "comment": "--"
        },
        {
          "owner": "Self",
          "ticker": "FRIAX",
          "asset-name": "Franklin Income Adv (NASDAQ)",
          "transaction-type": "Purchase",
          "transaction-date": "04/04/2013",
          "amount": "$1,001 - $15,000",
          "comment": "--"
        },
        {
          "owner": "Self",
          "ticker": "JDEZX",
          "asset-name": "Prudential Jennison Equity Income Z (NASDAQ)",
          "transaction-type": "Purchase",
          "transaction-date": "04/04/2013",
          "amount": "$1,001 - $15,000",
          "comment": "--"
        },
        {
          "owner": "Self",
          "ticker": "NBHAX",
          "asset-name": "Neuberger Berman Equity Income A (NASDAQ)",
          "transaction-type": "Purchase",
          "transaction-date": "04/04/2013",
          "amount": "$1,001 - $15,000",
          "comment": "--"
        },
        {
          "owner": "Self",
          "ticker": "RRGAX",
          "asset-name": "DWS RREEF Global Real Estate Secs A (NASDAQ)",
          "transaction-type": "Purchase",
          "transaction-date": "04/04/2013",
          "amount": "$1,001 - $15,000",
          "comment": "--"
        },
        {
          "owner": "Self",
          "ticker": "SOPAX",
          "asset-name": "ClearBridge Equity Income A (NASDAQ)",
          "transaction-type": "Purchase",
          "transaction-date": "04/04/2013",
          "amount": "$1,001 - $15,000",
          "comment": "--"
        },
        {
          "owner": "Self",
          "ticker": "SVAIX",
          "asset-name": "Federated Strategic Value Dividend Instl (NASDAQ)",
          "transaction-type": "Purchase",
          "transaction-date": "04/04/2013",
          "amount": "$1,001 - $15,000",
          "comment": "--"
        },
        {
          "owner": "Self",
          "ticker": "PPSPX",
          "asset-name": "Principal Preferred Securities P (NASDAQ)",
          "transaction-type": "Purchase",
          "transaction-date": "04/04/2013",
          "amount": "$1,001 - $15,000",
          "comment": "--"
        },
        {
          "owner": "Self",
          "ticker": "NBHAX",
          "asset-name": "Neuberger Berman Equity Income A (NASDAQ)",
          "transaction-type": "Sale (Full)",
          "transaction-date": "11/18/2013",
          "amount": "$50,001 - $100,000",
          "comment": "--"
        },
        {
          "owner": "Self",
          "ticker": "RRGAX",
          "asset-name": "DWS RREEF Global Real Estate Secs A (NASDAQ)",
          "transaction-type": "Sale (Full)",
          "transaction-date": "11/18/2013",
          "amount": "$1,001 - $15,000",
          "comment": "--"
        },
        {
          "owner": "Self",
          "ticker": "PMDPX",
          "asset-name": "Principal Small-MidCap Dividend Inc P (NASDAQ)",
          "transaction-type": "Purchase",
          "transaction-date": "11/18/2013",
          "amount": "$50,001 - $100,000",
          "comment": "--"
        },
        {
          "owner": "Self",
          "ticker": "MMUFX",
          "asset-name": "MFS Utilities A (NASDAQ)",
          "transaction-type": "Sale (Partial)",
          "transaction-date": "11/18/2013",
          "amount": "$1,001 - $15,000",
          "comment": "--"
        },
        {
          "owner": "Self",
          "ticker": "SVAIX",
          "asset-name": "Federated Strategic Value Dividend Instl (NASDAQ)",
          "transaction-type": "Sale (Partial)",
          "transaction-date": "11/18/2013",
          "amount": "$1,001 - $15,000",
          "comment": "--"
        },
        {
          "owner": "Self",
          "ticker": "GNEIX",
          "asset-name": "Geneva Advisors Equity Income I (NASDAQ)",
          "transaction-type": "Purchase",
          "transaction-date": "11/20/2013",
          "amount": "$15,001 - $50,000",
          "comment": "--"
        },
        {
          "owner": "Self",
          "ticker": "ARIDX",
          "asset-name": "ASTON/River Road Dividend All Cap Val I (NASDAQ)",
          "transaction-type": "Sale (Partial)",
          "transaction-date": "11/25/2013",
          "amount": "$1,001 - $15,000",
          "comment": "--"
        },
        {
          "owner": "Self",
          "ticker": "GNEIX",
          "asset-name": "Geneva Advisors Equity Income I (NASDAQ)",
          "transaction-type": "Purchase",
          "transaction-date": "11/25/2013",
          "amount": "$1,001 - $15,000",
          "comment": "--"
        },
        {
          "owner": "Self",
          "ticker": "CAIFX",
          "asset-name": "American Funds Capital Inc Bldr F2 (NASDAQ)",
          "transaction-type": "Sale (Partial)",
          "transaction-date": "11/25/2013",
          "amount": "$1,001 - $15,000",
          "comment": "--"
        },
        {
          "owner": "Self",
          "ticker": "EPSPX",
          "asset-name": "MainStay Epoch Global Equity Yield A (NASDAQ)",
          "transaction-type": "Sale (Partial)",
          "transaction-date": "11/25/2013",
          "amount": "$1,001 - $15,000",
          "comment": "--"
        },
        {
          "owner": "Self",
          "ticker": "JDEZX",
          "asset-name": "Prudential Jennison Equity Income Z (NASDAQ)",
          "transaction-type": "Sale (Partial)",
          "transaction-date": "11/25/2013",
          "amount": "$1,001 - $15,000",
          "comment": "--"
        },
        {
          "owner": "Self",
          "ticker": "MMUFX",
          "asset-name": "MFS Utilities A (NASDAQ)",
          "transaction-type": "Sale (Partial)",
          "transaction-date": "11/25/2013",
          "amount": "$1,001 - $15,000",
          "comment": "--"
        },
        {
          "owner": "Self",
          "ticker": "FRIAX",
          "asset-name": "Franklin Income Adv (NASDAQ)",
          "transaction-type": "Sale (Partial)",
          "transaction-date": "11/25/2013",
          "amount": "$1,001 - $15,000",
          "comment": "--"
        },
        {
          "owner": "Self",
          "ticker": "SVAIX",
          "asset-name": "Federated Strategic Value Dividend Instl (NASDAQ)",
          "transaction-type": "Sale (Partial)",
          "transaction-date": "11/25/2013",
          "amount": "$1,001 - $15,000",
          "comment": "--"
        },
        {
          "owner": "Self",
          "ticker": "SOPAX",
          "asset-name": "ClearBridge Equity Income A (NASDAQ)",
          "transaction-type": "Sale (Partial)",
          "transaction-date": "11/25/2013",
          "amount": "$1,001 - $15,000",
          "comment": "--"
        },
        {
          "owner": "Self",
          "ticker": "PMDPX",
          "asset-name": "Principal Small-MidCap Dividend Inc P (NASDAQ)",
          "transaction-type": "Sale (Partial)",
          "transaction-date": "11/25/2013",
          "amount": "$1,001 - $15,000",
          "comment": "--"
        },
        {
          "owner": "Self",
          "ticker": "PPSPX",
          "asset-name": "Principal Preferred Securities P (NASDAQ)",
          "transaction-type": "Purchase",
          "transaction-date": "11/26/2013",
          "amount": "$1,001 - $15,000",
          "comment": "--"
        },
        {
          "owner": "Spouse",
          "ticker": "IDITX",
          "asset-name": "Transamerica Flexible Income A (NASDAQ)",
          "transaction-type": "Sale (Partial)",
          "transaction-date": "11/08/2013",
          "amount": "$1,001 - $15,000",
          "comment": "--"
        },
        {
          "owner": "Self",
          "ticker": "RRGAX",
          "asset-name": "DWS RREEF Global Real Estate Secs A (NASDAQ)",
          "transaction-type": "Purchase",
          "transaction-date": "12/19/2013",
          "amount": "$1,001 - $15,000",
          "comment": "--"
        },
        {
          "owner": "Self",
          "ticker": "PPSPX",
          "asset-name": "Principal Preferred Securities P (NASDAQ)",
          "transaction-type": "Purchase",
          "transaction-date": "12/19/2013",
          "amount": "$1,001 - $15,000",
          "comment": "--"
        },
        {
          "owner": "Self",
          "ticker": "JDEZX",
          "asset-name": "Prudential Jennison Equity Income Z (NASDAQ)",
          "transaction-type": "Purchase",
          "transaction-date": "12/23/2013",
          "amount": "$1,001 - $15,000",
          "comment": "--"
        },
        {
          "owner": "Self",
          "ticker": "ARIDX",
          "asset-name": "ASTON/River Road Dividend All Cap Val I (NASDAQ)",
          "transaction-type": "Purchase",
          "transaction-date": "12/31/2013",
          "amount": "$1,001 - $15,000",
          "comment": "--"
        },
        {
          "owner": "Self",
          "ticker": "GNEIX",
          "asset-name": "Geneva Advisors Equity Income I (NASDAQ)",
          "transaction-type": "Purchase",
          "transaction-date": "12/31/2013",
          "amount": "$1,001 - $15,000",
          "comment": "--"
        },
        {
          "owner": "Joint",
          "ticker": "GAFYX",
          "asset-name": "Natixis ASG Global Alternatives Y (NASDAQ)",
          "transaction-type": "Sale (Full)",
          "transaction-date": "04/30/2013",
          "amount": "$1,001 - $15,000",
          "comment": "--"
        },
        {
          "owner": "Joint",
          "ticker": "PCRPX",
          "asset-name": "PIMCO Commodity Real Return Strat P (NASDAQ)",
          "transaction-type": "Sale (Full)",
          "transaction-date": "04/30/2013",
          "amount": "$1,001 - $15,000",
          "comment": "--"
        },
        {
          "owner": "Joint",
          "ticker": "ACINX",
          "asset-name": "Columbia Acorn International Z (NASDAQ)",
          "transaction-type": "Purchase",
          "transaction-date": "04/30/2013",
          "amount": "$1,001 - $15,000",
          "comment": "--"
        },
        {
          "owner": "Joint",
          "ticker": "RSIGX",
          "asset-name": "RS International Y (NASDAQ)",
          "transaction-type": "Sale (Full)",
          "transaction-date": "04/30/2013",
          "amount": "$1,001 - $15,000",
          "comment": "--"
        },
        {
          "owner": "Joint",
          "ticker": "MYSIX",
          "asset-name": "Munder International Small-Cap Y (NASDAQ)",
          "transaction-type": "Sale (Full)",
          "transaction-date": "04/30/2013",
          "amount": "$1,001 - $15,000",
          "comment": "--"
        },
        {
          "owner": "Joint",
          "ticker": "MQGIX",
          "asset-name": "MFS International Growth I (NASDAQ)",
          "transaction-type": "Purchase",
          "transaction-date": "04/30/2013",
          "amount": "$1,001 - $15,000",
          "comment": "--"
        },
        {
          "owner": "Joint",
          "ticker": "AQMNX",
          "asset-name": "AQR Managed Futures Strategy N (NASDAQ)",
          "transaction-type": "Purchase",
          "transaction-date": "05/02/2013",
          "amount": "$15,001 - $50,000",
          "comment": "--"
        },
        {
          "owner": "Joint",
          "ticker": "NFEAX",
          "asset-name": "Columbia Marsico Focused Equities A (NASDAQ)",
          "transaction-type": "Purchase",
          "transaction-date": "06/26/2013",
          "amount": "$1,001 - $15,000",
          "comment": "--"
        },
        {
          "owner": "Joint",
          "ticker": "NFEAX",
          "asset-name": "Columbia Marsico Focused Equities A (NASDAQ)",
          "transaction-type": "Sale (Full)",
          "transaction-date": "07/15/2013",
          "amount": "$15,001 - $50,000",
          "comment": "--"
        },
        {
          "owner": "Joint",
          "ticker": "BIAGX",
          "asset-name": "Brown Advisory Growth Equity Inv (NASDAQ)",
          "transaction-type": "Purchase",
          "transaction-date": "07/17/2013",
          "amount": "$15,001 - $50,000",
          "comment": "--"
        },
        {
          "owner": "Joint",
          "ticker": "TSCPX",
          "asset-name": "AMG TimesSquare Small Cap Growth Prem (NASDAQ)",
          "transaction-type": "Purchase",
          "transaction-date": "08/26/2013",
          "amount": "$1,001 - $15,000",
          "comment": "--"
        },
        {
          "owner": "Joint",
          "ticker": "JLPSX",
          "asset-name": "JPMorgan US Large Cap Core Plus Select (NASDAQ)",
          "transaction-type": "Purchase",
          "transaction-date": "12/13/2013",
          "amount": "$1,001 - $15,000",
          "comment": "--"
        },
        {
          "owner": "Joint",
          "ticker": "JVLAX",
          "asset-name": "JHancock Disciplined Value A (NASDAQ)",
          "transaction-type": "Purchase",
          "transaction-date": "12/17/2013",
          "amount": "$1,001 - $15,000",
          "comment": "--"
        },
        {
          "owner": "Joint",
          "ticker": "EXEYX",
          "asset-name": "Manning & Napier Equity (NASDAQ)",
          "transaction-type": "Purchase",
          "transaction-date": "12/17/2013",
          "amount": "$1,001 - $15,000",
          "comment": "--"
        },
        {
          "owner": "Joint",
          "ticker": "NBGNX",
          "asset-name": "Neuberger Berman Genesis Inv (NASDAQ)",
          "transaction-type": "Purchase",
          "transaction-date": "12/17/2013",
          "amount": "$1,001 - $15,000",
          "comment": "--"
        },
        {
          "owner": "Joint",
          "ticker": "HIEMX",
          "asset-name": "Virtus Emerging Markets Opportunities I (NASDAQ)",
          "transaction-type": "Purchase",
          "transaction-date": "04/30/2013",
          "amount": "$1,001 - $15,000",
          "comment": "--"
        },
        {
          "owner": "Joint",
          "ticker": "JVTAX",
          "asset-name": "Janus Venture A (NASDAQ)",
          "transaction-type": "Sale (Full)",
          "transaction-date": "08/26/2013",
          "amount": "$1,001 - $15,000",
          "comment": "--"
        }
      ]
    },
    {
      "heading": "Part 5. Gifts",
      "amended": false,
      "rows": []
    },
    {
      "heading": "Part 6. Travel",
      "amended": false,
      "rows": []
    },
    {
      "heading": "Part 7. Liabilities",
      "amended": false,
      "rows": []
    },
    {
      "heading": "Part 8. Positions",
      "amended": false,
      "rows": [
        {
          "position-dates": "Jul 1964 to\n\t\t\t\t\t\t\t\tpresent",
          "position-held": "Proprietor",
          "entity": "Farm-Butler County Iowa\n\t\t\t\t\t\t\t\t\n\t\t\t\t\t\t\t\t\tNew Hartford & Cedar Falls, IA",
          "entity-type": "Other\n\t\t\t\t\t\t\t\t(Family Farm Operation)",
          "comments": ""
        }
      ]
    },
    {
      "heading": "Part 9. Agreements",
      "amended": false,
      "rows": []
    },
    {
      "heading": "Part 10. Compensation",
      "amended": false,
      "rows": []
    },
    {
      "heading": "Attachments & Comments",
      "amended": false,
      "rows": []
    }
  ]
}