{
  "type": "periodic transaction",
  "title": "Periodic Transaction Report for 04/12/2019",
  "filer": "The Honorable John Hoeven (Hoeven, John)",
  "filed-date": "04/12/2019",
  "filed-time": "11:01 AM",
  "calendar-year": null,
  "data-entry-complete": true,
  "data": [
    {
      "heading": "Transactions",
      "amended": false,
      "rows": [
        {
          "transaction-date": "04/09/2019",
          "owner": "Self",
          "ticker": "--",
          "asset-name": "Westbrand, Inc.\n                                        \n                                        \n                                        \n                                            \n                                                \n                                                    Company: Westbrand, Inc.\n                                                    \n                                                         (Minot, North Dakota)\n                                                    \n                                                \n                                            \n\n                                            \n                                                Description: Bank holding company of First Western Bank",
          "asset-type": "Non-Public Stock",
          "type": "Purchase",
          "amount": "$15,001 - $50,000",
          "comment": "--"
        }
      ]
    }
  ]
}