{
  "type": "periodic transaction",
  "title": "Periodic Transaction Report for 04/28/2014",
  "filer": "The Honorable Sheldon Whitehouse (Whitehouse, Sheldon)",
  "filed-date": "04/28/2014",
  "filed-time": "10:20 AM",
  "calendar-year": null,
  "data-entry-complete": true,
  "data": [
    {
      "heading": "Transactions",
      "amended": false,
      "rows": [
        {
          "transaction-date": "04/11/2014",
          "owner": "Joint",
          "ticker": "V",
          "asset-name": "Visa Inc. (NYSE)",
          "asset-type": "",
          "type": "Purchase",
          "amount": "$1,001 - $15,000",
          "comment": "--"
        },
        {
          "transaction-date": "03/20/2014",
          "owner": "Joint",
          "ticker": "C",
          "asset-name": "Citigroup Inc. (NYSE)",
          "asset-type": "",
          "type": "Purchase",
          "amount": "$1,001 - $15,000",
          "comment": "--"
        },
        {
          "transaction-date": "03/20/2014",
          "owner": "Joint",
          "ticker": "SLB",
          "asset-name": "Schlumberger Limited (NYSE)",
          "asset-type": "",
          "type": "Purchase",
          "amount": "$1,001 - $15,000",
          "comment": "--"
        }
      ]
    }
  ]
}