{
  "title": "Periodic Transaction Report for 09/07/2018",
  "filer": "The Honorable Sheldon Whitehouse (Whitehouse, Sheldon)",
  "filedDate": "Filed 09/07/2018 @ 3:22 PM",
  "data": [
    {
      "heading": "Transactions",
      "rows": [
        {
          "#": "8",
          "Transaction Date": "08/28/2018",
          "Owner": "Spouse",
          "Ticker": "GS",
          "Asset Name": "The Goldman Sachs Group, Inc.",
          "Asset Type": "Stock",
          "Type": "Purchase",
          "Amount": "$1,001 - $15,000",
          "Comment": "--"
        },
        {
          "#": "7",
          "Transaction Date": "08/28/2018",
          "Owner": "Spouse",
          "Ticker": "T",
          "Asset Name": "AT&T Inc.",
          "Asset Type": "Stock",
          "Type": "Purchase",
          "Amount": "$1,001 - $15,000",
          "Comment": "--"
        },
        {
          "#": "6",
          "Transaction Date": "08/28/2018",
          "Owner": "Spouse",
          "Ticker": "BABA",
          "Asset Name": "Alibaba Group Holding Limited",
          "Asset Type": "Stock",
          "Type": "Purchase",
          "Amount": "$1,001 - $15,000",
          "Comment": "--"
        },
        {
          "#": "5",
          "Transaction Date": "08/28/2018",
          "Owner": "Spouse",
          "Ticker": "LRCX",
          "Asset Name": "Lam Research Corporation",
          "Asset Type": "Stock",
          "Type": "Purchase",
          "Amount": "$1,001 - $15,000",
          "Comment": "--"
        },
        {
          "#": "4",
          "Transaction Date": "08/28/2018",
          "Owner": "Spouse",
          "Ticker": "WMT",
          "Asset Name": "Walmart Inc.",
          "Asset Type": "Stock",
          "Type": "Purchase",
          "Amount": "$1,001 - $15,000",
          "Comment": "--"
        },
        {
          "#": "3",
          "Transaction Date": "08/28/2018",
          "Owner": "Joint",
          "Ticker": "WMT",
          "Asset Name": "Walmart Inc.",
          "Asset Type": "Stock",
          "Type": "Purchase",
          "Amount": "$15,001 - $50,000",
          "Comment": "--"
        },
        {
          "#": "2",
          "Transaction Date": "08/06/2018",
          "Owner": "Self",
          "Ticker": "T",
          "Asset Name": "AT&T Inc.",
          "Asset Type": "Stock",
          "Type": "Purchase",
          "Amount": "$1,001 - $15,000",
          "Comment": "--"
        },
        {
          "#": "1",
          "Transaction Date": "08/06/2018",
          "Owner": "Self",
          "Ticker": "BRK-B",
          "Asset Name": "Berkshire Hathaway Inc.",
          "Asset Type": "Stock",
          "Type": "Purchase",
          "Amount": "$1,001 - $15,000",
          "Comment": "--"
        }
      ]
    }
  ]
}